<?xml version="1.0" encoding="utf-8"?>
<search>
  
  
  
  <entry>
    <title>线上支教</title>
    <link href="/2022/05/08/Daily-1%20%E7%BA%BF%E4%B8%8A%E6%94%AF%E6%95%99/"/>
    <url>/2022/05/08/Daily-1%20%E7%BA%BF%E4%B8%8A%E6%94%AF%E6%95%99/</url>
    
    <content type="html"><![CDATA[<blockquote><p><a href="https://cloud.tsinghua.edu.cn/lib/9fcff28a-37a6-486e-b569-0b70e575a646/file/%E5%85%B6%E5%AE%83/%E9%9B%86%E5%90%88%2B%E5%87%BD%E6%95%B0%EF%BC%881%EF%BC%89.pptx">支教PPT——集合、函数</a></p></blockquote><h2 id="心得体会"><a href="#心得体会" class="headerlink" title="心得体会"></a>心得体会</h2><p>回想一下，当时为何想参加这个活动呢？一是想参加一些没体验过的志愿，二是想认识一些人，大概就这些原因了吧。自然也是对教书育人有憧憬的，很长一段时间的理想之一都是当个老师；不过近来多少有些不情愿，或者说，更想留在大学。</p><p>我知道我心里一直是喜欢小孩子的，只不过要求有点高，年龄太小的不行，太玩闹的不行，太笨的也不行。这么说来，似乎小学、初中、高中的老师都难免不太能符合这些条件。</p><p>或许多少是有些自私的吧。</p><p>说回支教，总感觉就像一场梦一样，前期准备了很多，但是那么三四十分钟很快就过去了，心里预设的那些紧张、期待、迷茫，也好像都没有发生一样。我似乎就只是讲我能讲的东西，小朋友们似乎像是不存在的一样。然后就结束了。</p><p>人生的某些节点，都像是这样子，你似乎只是照着心里的想法做，做着做着，就结束了。中途或有种种困难，但似乎也没有花太大的气力去解决，只是照常地做下去而已。不免让人产生一种如梦如幻之感。</p><p>但也是有一些经验教训可谈的。原以为自己准备的内容并不困难，但真正讲的时候却也犯了不少错误，似乎也高估了小朋友们的水平。所以说教书实难。表面上是教给他们，实际上竟也是在和自己较劲。</p><p>就写这么点吧。实际意义上的第一篇博客，没想到记录了这么一件事儿。文笔也有些不堪品读，然而至少真实，也就够了。</p><p>如上。</p>]]></content>
    
    
    
  </entry>
  
  
  
  
</search>
